[
    {
        "index": 0,
        "name": "Weather App",
        "codeBase": "GitHub",
        "urlLive": "https://weather-td.netlify.app/",
        "urlCode": "https://github.com/TutulDevs/weatherApp",
        "notes": "API, events"
    },
    {
        "index": 1,
        "name": "Drum Kit",
        "codeBase": "GitHub",
        "urlLive": "https://all-js.netlify.app/04-drumKit",
        "urlCode": "https://github.com/TutulDevs/All-JavaScript/tree/master/04-drumKit",
        "notes": "transitionend, audio(play, volume), PWA"
    },
    {
        "index": 2,
        "name": "DemoLive",
        "codeBase": "DemoCode",
        "urlLive": "#",
        "urlCode": "#",
        "notes": "DemoNote"
    }
]
